Metadata-Version: 2.1
Name: minio-async
Version: 1.0.1
Summary: Asynchronous MinIO Python SDK for Amazon S3 Compatible Cloud Storage
Home-page: https://github.com/HuseynMashadiyev/minio-async
Author: Huseyn Mashadiyev
Author-email: mashadiyev.huseyn@gmail.com
License: Apache License 2.0
Classifier: Development Status :: 5 - Production/Stable
Classifier: Intended Audience :: Developers
Classifier: License :: OSI Approved :: Apache Software License
Classifier: Natural Language :: English
Classifier: Operating System :: OS Independent
Classifier: Programming Language :: Python
Classifier: Programming Language :: Python :: 3.6
Classifier: Programming Language :: Python :: 3.7
Classifier: Programming Language :: Python :: 3.8
Classifier: Programming Language :: Python :: 3.9
Classifier: Topic :: Software Development :: Libraries :: Python Modules
License-File: LICENSE
Requires-Dist: certifi
Requires-Dist: aiofile
Requires-Dist: aiohttp
